changeip/__init__.py
changeip/changeip.py
changeip-1.0.1.dist-info/METADATA
changeip-1.0.1.dist-info/WHEEL
changeip-1.0.1.dist-info/top_level.txt
changeip-1.0.1.dist-info/RECORD
