Metadata-Version: 2.1
Name: changeip
Version: 1.0.1
Summary: changeip
Home-page: UNKNOWN
Author: Huzhiyong
Author-email: huzhiyong777@gmail.com
License: MIT Licence
Keywords: pip,changeip,privoxy
Platform: any
